aioget
