Metadata-Version: 1.1
Name: aioget
Version: 0.2.1
Summary: Async io command line download utility written in python
Home-page: https://github.com/phoemur/aioget
Author: Fernando Giannasi <phoemur@gmail.com>
Author-email: UNKNOWN
License: Unlicense
Download-URL: https://github.com/phoemur/aioget/tarball/0.2.1
Platform: UNKNOWN
Classifier: Environment :: Console
Classifier: License :: OSI Approved :: MIT License
Classifier: Operating System :: OS Independent
Classifier: Programming Language :: Python :: 3.5
Classifier: Programming Language :: Python :: 3.6
Classifier: Topic :: Software Development :: Libraries :: Python Modules
Classifier: Topic :: System :: Networking
Classifier: Topic :: Utilities
